Workbook

Sheet Goldin Matched
A1: # | B1: Platform | C1: Card | D1: Date | E1: Proceeds | F1: eBay Match | G1: eBay Cost | H1: Score | I1: CORRECTED COST | J1: Final Cost | K1: P&L | L1: Return
A2: 1 | B2: Goldin | C2: 2024 Panini Select Sparks Memorabilia Purple Prizm #38 Caitlin Clark Signed Relic Rookie Card (#26/49) - PSA Authentic, PSA/DNA GEM MT 10 | D2: 2026-05-22 | E2: 501.4 | F2: 2024 Select WNBA #38 Caitlin Clark Rookie Purple Memorabilia /49 PSA GEM 10 AUTO | G2: 7000 | H2: 30 | J2: =IF(I2<>"",I2,G2) | K2: =E2-J2 | L2: =IF(J2>0,K2/J2,"")
A3: 2 | B3: Goldin | C3: 2006-07 Upper Deck Hardcourt #13 Michael Jordan - PSA GEM MT 10 | D3: 2026-03-13 | E3: 322 | F3: MICHAEL JORDAN 2013 Upper Deck All- Time Greats on card AUTO Autograph /45 | G3: 5600 | H3: 18 | J3: =IF(I3<>"",I3,G3) | K3: =E3-J3 | L3: =IF(J3>0,K3/J3,"")
A4: 3 | B4: Goldin | C4: 1986-87 Fleer #57 Michael Jordan Rookie Card - PSA NM-MT 8 (OC) | D4: 2026-05-14 | E4: 7475 | F4: 🔥1986-87 Fleer - #57 Michael Jordan (RC) GREATEST BASKETBALL PLAYER/CARD EVER! | G4: 12500 | H4: 26 | J4: =IF(I4<>"",I4,G4) | K4: =E4-J4 | L4: =IF(J4>0,K4/J4,"")
A5: 4 | B5: Goldin | C5: 2024 Panini Prizm #22 Caitlin Clark Rookie Card - PSA GEM MT 10 | D5: 2026-05-15 | E5: 201.25 | F5: 2024 Panini Prizm WNBA #22 Caitlin Clark Orange Ice Rookie PSA GEM MINT 10 AUTO | G5: 5000 | H5: 28 | J5: =IF(I5<>"",I5,G5) | K5: =E5-J5 | L5: =IF(J5>0,K5/J5,"")
A6: 5 | B6: Goldin | C6: 2024 Panini Prizm WNBA Blue Velocity Prizm #22 Caitlin Clark Rookie Card - PSA GEM MT 10 | D6: 2026-05-15 | E6: 402.5 | F6: 2024 Panini Prizm WNBA #22 Caitlin Clark Orange Ice Rookie PSA GEM MINT 10 AUTO | G6: 5000 | H6: 30 | J6: =IF(I6<>"",I6,G6) | K6: =E6-J6 | L6: =IF(J6>0,K6/J6,"")
A7: 6 | B7: Goldin | C7: 1997-98 Topps Stadium Club Triumvirate Luminous #T9B Michael Jordan - PSA NM-MT 8 | D7: 2026-05-10 | E7: 1443.25 | F7: 1997-98 Stadium Club Triumvirate - Michael Jordan #T9B BGS 9.5 | G7: 6000 | H7: 25 | J7: =IF(I7<>"",I7,G7) | K7: =E7-J7 | L7: =IF(J7>0,K7/J7,"")
A8: 7 | B8: Goldin | C8: 2022-23 Panini Donruss FIFA Kaboom! #2 Lionel Messi - PSA GEM MT 10 | D8: 2026-06-23 | E8: 9775 | F8: Lionel Messi 2022 Panini Donruss Kaboom ! PSA 10 gem mint | G8: 13750 | H8: 23 | J8: =IF(I8<>"",I8,G8) | K8: =E8-J8 | L8: =IF(J8>0,K8/J8,"")
A9: 8 | B9: Goldin | C9: 2018-19 Panini Impeccable Stainless Stars Autograph #SA-SGA Shai Gilgeous-Alexander Signed Rookie Card (#74/99) - PSA Authentic, PSA/DNA GEM MT 10 | D9: 2026-04-18 | E9: 1840 | F9: SHAI GILGEOUS-ALEXANDER 2018-19 PANINI FLAWLESS #RA-SGA ROOKIE AUTO RUBY RC 9/15 | G9: 5100 | H9: 20 | J9: =IF(I9<>"",I9,G9) | K9: =E9-J9 | L9: =IF(J9>0,K9/J9,"")
A10: 9 | B10: Goldin | C10: 2022-23 Panini Flawless Autographs Emerald '25 Black Box #FA-SGA Shai Gilgeous-Alexander Signed Card (#1/1) - Panini Encased | D10: 2026-05-10 | E10: 1955 | F10: SHAI GILGEOUS-ALEXANDER 2018-19 PANINI FLAWLESS #RA-SGA ROOKIE AUTO RUBY RC 9/15 | G10: 5100 | H10: 20 | J10: =IF(I10<>"",I10,G10) | K10: =E10-J10 | L10: =IF(J10>0,K10/J10,"")
A11: 10 | B11: Goldin | C11: 2018-19 Panini National Treasures Rookie Materials Prime #RM-SGA Shai Gilgeous-Alexander Signed Patch Rookie Card (#03/25) - PSA Authentic, PSA/DNA GEM MT 10 | D11: 2026-06-15 | E11: 2185 | F11: SHAI GILGEOUS-ALEXANDER 2018-19 PANINI FLAWLESS #RA-SGA ROOKIE AUTO RUBY RC 9/15 | G11: 5100 | H11: 22 | J11: =IF(I11<>"",I11,G11) | K11: =E11-J11 | L11: =IF(J11>0,K11/J11,"")
A12: 11 | B12: Goldin | C12: 2024-25 Panini Flawless Phrases Signatures #FPS-SGA Shai Gilgeous-Alexander Signed Card (#4/5) - Panini Encased | D12: 2026-05-11 | E12: 2185 | F12: SHAI GILGEOUS-ALEXANDER 2018-19 PANINI FLAWLESS #RA-SGA ROOKIE AUTO RUBY RC 9/15 | G12: 5100 | H12: 20 | J12: =IF(I12<>"",I12,G12) | K12: =E12-J12 | L12: =IF(J12>0,K12/J12,"")
A13: 12 | B13: Goldin | C13: 2021-22 Panini National Treasures Clutch Factor Signatures #CF-SCU Stephen Curry Signed Relic Card (#09/25) - Panini Encased | D13: 2026-04-13 | E13: 1725 | F13: 2023 Panini Flawless Stephen Curry Scoring Title Auto #FST-SCU /25 PSA 9/10 | G13: 4350 | H13: 13 | J13: =IF(I13<>"",I13,G13) | K13: =E13-J13 | L13: =IF(J13>0,K13/J13,"")
... A190: 189 | B190: Goldin | C190: 2023-24 Topps Royalty Patch Autographs #115 Victor Wembanyama Signed Patch Rookie Card (#98/99) - PSA NM-MT 8 | D190: 2026-06-11 | E190: 13800 | F190: Dwyane Wade Miami Heat 2003 Topps Chrome Refractor Rookie Card #115 PSA 9 | G190: 450 | H190: 16 | J190: =IF(I190<>"",I190,G190) | K190: =E190-J190 | L190: =IF(J190>0,K190/J190,"")
A192: 191 | B192: Goldin | C192: 2012-13 Upper Deck Exquisite Collection UD Black Signatures #B-MI Michael Jordan Signed Card (#33/75) - PSA GEM MT 10 | E192: 10465 | F192: Michael Jordan 2012-13 UD Exquisite Black Signatures Autograph #59/75 BGS 9.5 | G192: 5250 | H192: 22 | J192: =IF(I192<>"",I192,G192) | K192: =E192-J192 | L192: =IF(J192>0,K192/J192,"")
A193: 192 | B193: Goldin | C193: 2023-24 Topps Chrome 1972 Topps Autographs Gold Refractor #TA-VW Victor Wembanyama Signed Rookie Card (#04/50) - PSA MINT 9 | E193: 7123.1 | F193: 2023-24 Topps Chrome Victor Wembanyama 1972 Auto Gold Refractor RC #4/50 Spurs | G193: 2025 | H193: 26 | J193: =IF(I193<>"",I193,G193) | K193: =E193-J193 | L193: =IF(J193>0,K193/J193,"")
A194: 193 | B194: Goldin | C194: 2025-26 Topps Silver Pack '80-81 Chrome Basketball Rookie Autographs Orange Refractor #80CR2-CF Cooper Flagg Signed Rookie Card (#17/25) - PSA MINT 9, PSA/DNA GEM MT 10 | E194: 4427.5 | F194: Will Riley 2025 Topps Chrome #80CR2-WR Orange Mojo Refractor Rookie Auto RC /25 | G194: 122.5 | H194: 30 | J194: =IF(I194<>"",I194,G194) | K194: =E194-J194 | L194: =IF(J194>0,K194/J194,"")
A195: 194 | B195: Goldin | C195: 2018-19 Panini National Treasures Peerless Signatures #PS-KBR Kobe Bryant Signed Card (#03/25) - BGS MINT 9, Beckett 10 | E195: 4025 | F195: 2018 National Treasures Kobe Bryant Peerless Auto #6 /25 BGS 9/10 | G195: 6180 | H195: 20 | J195: =IF(I195<>"",I195,G195) | K195: =E195-J195 | L195: =IF(J195>0,K195/J195,"")
A196: 195 | B196: Goldin | C196: 2015-16 Panini Noir Autographs Color Gold #NC-KBR Kobe Bryant Signed Card (#4/5) - PSA EX-MT 6 - Pop 1 | E196: 3795 | F196: KOBE BRYANT 2015-16 PANINI NOIR AUTOGRAPH GOLD INK LAKERS AUTO /5 Q3873 | G196: 3550 | H196: 24 | J196: =IF(I196<>"",I196,G196) | K196: =E196-J196 | L196: =IF(J196>0,K196/J196,"")
A197: 196 | B197: Goldin | C197: 2018 Panini Kaboom! #K-NJ Neymar Jr. - PSA GEM MT 10 | E197: 3576.5 | F197: 2018 Panini Kaboom Neymar Jr. #NJ PSA 10 GEM MINT Brazil Low POP Rare | G197: 4000 | H197: 17 | J197: =IF(I197<>"",I197,G197) | K197: =E197-J197 | L197: =IF(J197>0,K197/J197,"")
A198: 197 | B198: Goldin | C198: 2003-04 Upper Deck Top Prospects Signs of Success #SS-LJ LeBron James Signed Rookie Card - BGS MINT 9, Beckett 10 | E198: 3047.5 | F198: LeBron James Rookie Card 2003 UD Top Prospects Signs Of Success BGS 9 Auto 10 | G198: 2800 | H198: 17 | J198: =IF(I198<>"",I198,G198) | K198: =E198-J198 | L198: =IF(J198>0,K198/J198,"")
A199: 198 | B199: Goldin | C199: 2025-26 Topps Chrome Future Stars Autographs Green Refractor #FS-CF Cooper Flagg Signed Rookie Card (#43/99) - PSA MINT 9, PSA/DNA GEM MT 10 | E199: 2760 | F199: 2025-26 Topps Chrome Cooper Flagg Future Stars Auto Green Refractor RC #/99 | G199: 2234 | H199: 26 | J199: =IF(I199<>"",I199,G199) | K199: =E199-J199 | L199: =IF(J199>0,K199/J199,"")
A200: 199 | B200: Goldin | C200: 2023-24 Bowman U Best of 2023 Autograph Geometric Red Refractor #B23-CC Caitlin Clark Signed Rookie Card (#01/10) - PSA MINT 9, PSA/DNA GEM MT 10 | E200: 2645 | F200: 2023 Bowman U Best CAITLIN CLARK Geo Red Refractor Auto /10 PSA 9/10 Iowa Fever | G200: 2700 | H200: 24 | J200: =IF(I200<>"",I200,G200) | K200: =E200-J200 | L200: =IF(J200>0,K200/J200,"")
A201: 200 | B201: Goldin | C201: 2020-21 Panini Flawless Draft Gem Signatures Ruby #DG-AEW Anthony Edwards Signed Rookie Card (#15/15) - Panini Encased | E201: 2601.3 | F201: 15/15 ≈1/1 2020-21 Panini Flawless Anthony Edwards Ruby Draft Gem Auto RC Rookie | G201: 2899 | H201: 26 | J201: =IF(I201<>"",I201,G201) | K201: =E201-J201 | L201: =IF(J201>0,K201/J201,"")
A202: 201 | B202: Goldin | C202: 2023-24 Topps Chrome UCC Future Stars Autographs SuperFractor #FSA-KM Kobbie Mainoo Signed Card (#1/1) - PSA NM-MT 8 | E202: 2472.5 | F202: 2023-24 Topps Royalty Zach LaVine Regalia Relic Patch Platinum Auto #1/1 | G202: 89.89 | H202: 22 | J202: =IF(I202<>"",I202,G202) | K202: =E202-J202 | L202: =IF(J202>0,K202/J202,"")
A203: 202 | B203: Goldin | C203: 2022-23 Bowman U Best of '22 Autographs #BOA-VW Victor Wembanyama Signed Rookie Card - PSA GEM MT 10 | E203: 2472.5 | F203: 2022-23 Bowman University - Victor Wembanyama Best of 2022 Auto PSA 10 | G203: 1550 | H203: 17 | J203: =IF(I203<>"",I203,G203) | K203: =E203-J203 | L203: =IF(J203>0,K203/J203,"")
... A264: 263 | B264: Goldin | C264: 2022-23 Panini Immaculate Collection Patch Autographs Jersey Number #IPA-RGO Rudy Gobert Signed Relic Card (#06/27) - Panini Encased | E264: 27.6 | F264: RUDY GOBERT 2022-23 IMMACULATE JERSEY NUMBER PATCH AUTOGRAPH AUTO /27 Q0218 | G264: 38 | H264: 22 | J264: =IF(I264<>"",I264,G264) | K264: =E264-J264 | L264: =IF(J264>0,K264/J264,"")
D265: TOTALS | E265: =SUM(E2:E264) | G265: =SUM(G2:G264) | J265: =SUM(J2:J264) | K265: =SUM(K2:K264) | L265: =IF(J265>0,K265/J265,"")

Sheet Goldin Unmatched
A1: # | B1: Platform | C1: Card | D1: Sale Date | E1: Net Proceeds | F1: Source (eBay or Fanatics?) | G1: ENTER COST | H1: P&L
A2: 1 | B2: Goldin | C2: 2019 Panini Flawless Triple Legends Sapphire #TL-MRG Mickey Mantle/Babe Ruth/Lou Gehrig Relic Card (#05/15) - PSA GEM MT 10 - Pop 2 | E2: 8051.15 | G2: 5000 | H2: =IF(G2<>"",E2-G2,"")
A3: 2 | B3: Goldin | C3: 2025 Panini Impeccable WNBA Basketball Factory-Sealed Hobby Case (3 Boxes) - Possible Paige Bueckers, Hailey Van Lith, Kiki Iriafen Rookie Cards | E3: 2876.15 | G3: 3600 | H3: =IF(G3<>"",E3-G3,"")
A4: 3 | B4: Goldin | C4: Feb. 27, 2013 - Stephen Curry Signed Full Ticket - Golden State Warriors vs. New York Knicks - Season Highs of 54 Points and 11 3-Pointers - PSA Authentic | E4: 529 | G4: 0 | H4: =IF(G4<>"",E4-G4,"")
A5: 4 | B5: Goldin | C5: Stephen Curry Signed Trading Card - PSA/DNA Authentic | E5: 380.65 | G5: 0 | H5: =IF(G5<>"",E5-G5,"")
A6: 5 | B6: Goldin | C6: 1997-98 Fleer Hoops 23k Gold Basketball Texture Bulls Starting Five - PSA GEM MT 10 | E6: 330.05 | G6: 0 | H6: =IF(G6<>"",E6-G6,"")
A7: 6 | B7: Goldin | C7: 2024-25 Topps Deluxe Manchester United Speak of the Devil Autograph Orange Refractor #SD-ZA Zlatan Ibrahimovic Signed Card (#07/25) - PSA MINT 9 - Pop 4 | E7: 178.25 | G7: 0 | H7: =IF(G7<>"",E7-G7,"")
A8: 7 | B8: Goldin | C8: Mike Tyson Signed Everlast Boxing Glove - Fiterman Sports | E8: 126.5 | G8: 0 | H8: =IF(G8<>"",E8-G8,"")
A9: 8 | B9: Goldin | C9: 2019-20 Panini One and One Dual Jersey Autographs Purple #DJA-DAF De'Aaron Fox Signed Relic Card (#06/35) - Panini Encased | E9: 75.9 | G9: 0 | H9: =IF(G9<>"",E9-G9,"")
A10: 9 | B10: Goldin | C10: Allen Iverson Signed Trading Card - PSA/DNA Authentic | E10: 71.3 | G10: 0 | H10: =IF(G10<>"",E10-G10,"")
D11: TOTALS | E11: =SUM(E2:E10) | G11: =SUM(G2:G10) | H11: =SUM(H2:H10)

Sheet FC Matched
A1: # | B1: Platform | C1: Card | D1: Sale Date | E1: Net Proceeds | F1: Fee% | G1: eBay Match | H1: eBay Cost | I1: Score | J1: CORRECTED COST | K1: Final Cost | L1: P&L | M1: Return
A2: 1 | B2: Fanatics Collect | C2: 2024 Donruss Optic Downtown Prizm Victor Wembanyama #16 PSA 10 GEM MINT | D2: 2026-05-19 | E2: 11000 | F2: 12 | G2: 2024 Panini Donruss Optic Victor Wembanyama Net Marvels Red Prizm /99 PSA 10 | H2: 600 | I2: 22 | K2: =IF(J2<>"",J2,H2) | L2: =E2-K2 | M2: =IF(K2>0,L2/K2,"")
A3: 2 | B3: Fanatics Collect | C3: 1997 Hoops Hooperstars Die-Cut Michael Jordan #1 PSA 10 GEM MINT | D3: 2026-05-19 | E3: 6486 | F3: 6 | G3: 1997-98 Fleer Flair Showcase Michael Jordan Row 3 #1 Bulls PSA 10 | H3: 1844 | I3: 26 | K3: =IF(J3<>"",J3,H3) | L3: =E3-K3 | M3: =IF(K3>0,L3/K3,"")
A4: 3 | B4: Fanatics Collect | C4: 2003 Topps Chrome LeBron James ROOKIE #111 BGS 9.5 GEM MINT | D4: 2026-06-02 | E4: 4183 | F4: 6 | G4: 2003 TOPPS CHROME #111 LEBRON JAMES ROOKIE RC PSA 9 | H4: 1950 | I4: 29 | K4: =IF(J4<>"",J4,H4) | L4: =E4-K4 | M4: =IF(K4>0,L4/K4,"")
A5: 4 | B5: Fanatics Collect | C5: 2024 Panini One And One Prizmania Stephen Curry #3 PSA 10 GEM MINT | D5: 2026-06-08 | E5: 4037.3 | F5: 6 | G5: Stephen Curry 2024-25 Panini One And One Metal Prizmania Case Hit SSP #3 | H5: 725 | I5: 29 | K5: =IF(J5<>"",J5,H5) | L5: =E5-K5 | M5: =IF(K5>0,L5/K5,"")
A6: 5 | B6: Fanatics Collect | C6: 2003 Topps Chrome LeBron James ROOKIE #111 BGS 9.5 GEM MINT | D6: 2026-06-02 | E6: 3995 | F6: 6 | G6: LEBRON JAMES PSA 10 2003-04 TOPPS CHROME BASKETBALL #111 ROOKIE GEM RC LAKERS | H6: 7505 | I6: 29 | K6: =IF(J6<>"",J6,H6) | L6: =E6-K6 | M6: =IF(K6>0,L6/K6,"")
A7: 6 | B7: Fanatics Collect | C7: 2003 Topps Chrome LeBron James ROOKIE #111 BGS 9.5 GEM MINT | D7: 2026-05-19 | E7: 3713 | F7: 6 | G7: 2003-04 Topps Chrome LeBron James #111 (RC) Rookie PSA 9 Mint | H7: 2199 | I7: 29 | K7: =IF(J7<>"",J7,H7) | L7: =E7-K7 | M7: =IF(K7>0,L7/K7,"")
A8: 7 | B8: Fanatics Collect | C8: 2024 Topps Jose Mourinho Platinum UEFA Euro European Future Purple Lamine Yamal AUTO /25 PSA 8 | D8: 2026-06-18 | E8: 3102 | F8: 6 | G8: 2024-25 Topps Finest UEFA Club Lamine Yamal Orange 19/25 Jersey Number Match 1/1 | H8: 461 | I8: 18 | K8: =IF(J8<>"",J8,H8) | L8: =E8-K8 | M8: =IF(K8>0,L8/K8,"")
A9: 8 | B9: Fanatics Collect | C9: 2023 Score FIFA Blue Lasers Lamine Yamal ROOKIE /50 #87 PSA 10 GEM MINT | D9: 2026-06-16 | E9: 2914 | F9: 6 | G9: Victor Wembanyama 2023-24 Select Blue Prizm SP #87 PSA 10 Rookie RC Concourse | H9: 100 | I9: 22 | K9: =IF(J9<>"",J9,H9) | L9: =E9-K9 | M9: =IF(K9>0,L9/K9,"")
A10: 9 | B10: Fanatics Collect | C10: 1992 Stadium Club Beam Team Michael Jordan #1 PSA 9 MINT | D10: 2026-06-14 | E10: 2900.84 | F10: 6 | G10: MICHAEL JORDAN 1998-99 Black Diamond #1 Double Red Serial #/3000 PSA 9 Pop 6, 4^ | H10: 183.5 | I10: 21 | K10: =IF(J10<>"",J10,H10) | L10: =E10-K10 | M10: =IF(K10>0,L10/K10,"")
A11: 10 | B11: Fanatics Collect | C11: 2023 Donruss FIFA Optic Ice Lamine Yamal ROOKIE #54 PSA 10 GEM MINT | D11: 2026-05-20 | E11: 2820 | F11: 6 | G11: 2023-24 Crystal Prem UEFA LAMINE YAMAL Rookie Purple Auto RC /99 PSA 10/10 Barca | H11: 2300 | I11: 18 | K11: =IF(J11<>"",J11,H11) | L11: =E11-K11 | M11: =IF(K11>0,L11/K11,"")
A12: 11 | B12: Fanatics Collect | C12: 2017 Panini Prizm Silver Patrick Mahomes II ROOKIE #269 BGS 9.5 GEM MINT | D12: 2026-05-16 | E12: 2444 | F12: 6 | G12: 2017 Prizm Patrick Mahomes II RC Rookie #269 Chiefs BGS 9.5 | H12: 3550 | I12: 30 | K12: =IF(J12<>"",J12,H12) | L12: =E12-K12 | M12: =IF(K12>0,L12/K12,"")
A13: 12 | B13: Fanatics Collect | C13: 2025 Topps Chrome Silver Pack '80 Gold LeBron James 1/50 #TC-LJ PSA 10 GEM MINT | D13: 2026-05-20 | E13: 2227.8 | F13: 6 | G13: 2025 Topps Chrome Gold Wave #127 LeBron James Lakers 30/50 PSA 10 POP 1 | H13: 3582 | I13: 25 | K13: =IF(J13<>"",J13,H13) | L13: =E13-K13 | M13: =IF(K13>0,L13/K13,"")
... A62: 61 | B62: Fanatics Collect | C62: 1996 Ultra All-Rookies Kobe Bryant ROOKIE #3 PSA 9 MINT | D62: 2026-06-18 | E62: 0 | F62: 0 | G62: 1996 Topps Youthquake Kobe Bryant Rookie Card PSA 9 MINT Graded Basketball #YQ15 | H62: 505 | I62: 18 | K62: =IF(J62<>"",J62,H62) | L62: =E62-K62 | M62: =IF(K62>0,L62/K62,"")
D63: TOTALS | E63: =SUM(E2:E62) | H63: =SUM(H2:H62) | K63: =SUM(K2:K62) | L63: =SUM(L2:L62) | M63: =IF(K63>0,L63/K63,"")

Sheet FC Unmatched
A1: # | B1: Platform | C1: Card | D1: Sale Date | E1: Net Proceeds | F1: Fee% | G1: Payout Status | H1: ENTER COST | I1: P&L
A2: 1 | B2: Fanatics Collect | C2: 2025 Topps MVP Collection Red Foil Shohei Ohtani & Aaron Judge PATCH 5/5 #50R | D2: 2026-06-18 | E2: 4465 | F2: 6 | G2: Payout complete | I2: =IF(H2<>"",E2-H2,"")
A3: 2 | B3: Fanatics Collect | C3: 2021 Bowman Chrome Orange Refractor Jordan Lawlar PROSPECT AUTO /25 PSA 10 GEM MINT | D3: 2026-06-10 | E3: 2303 | F3: 6 | G3: Payout complete | I3: =IF(H3<>"",E3-H3,"")
A4: 3 | B4: Fanatics Collect | C4: 2006 Finest Black Refractor LeBron James /99 #22 BGS 9.5 GEM MINT | D4: 2026-06-20 | E4: 2199.6 | F4: 6 | G4: Payout complete | I4: =IF(H4<>"",E4-H4,"")
A5: 4 | B5: Fanatics Collect | C5: 2003 Bowman Rookies & Stars Gold LeBron James ROOKIE #123 PSA 8 NM-MT | D5: 2026-05-14 | E5: 2021 | F5: 6 | G5: Payout complete | I5: =IF(H5<>"",E5-H5,"")
A6: 5 | B6: Fanatics Collect | C6: 2019 Crown Royale Kaboom! Giannis Antetokounmpo #11 BGS 9.5 GEM MINT | D6: 2026-05-05 | E6: 1927 | F6: 6 | G6: Payout complete | I6: =IF(H6<>"",E6-H6,"")
A7: 6 | B7: Fanatics Collect | C7: 2024 Finest UEFA CC Magenta Refractor Lamine Yamal AUTO /75 #BA-YL CGC AUTH | D7: 2026-06-18 | E7: 1510.08 | F7: 12 | G7: Payout complete | I7: =IF(H7<>"",E7-H7,"")
A8: 7 | B8: Fanatics Collect | C8: 2014 Panini Spectra Millenial Green Prizm Stephen Curry PATCH /5 #MM-SC BGS 9.5 GEM MINT | D8: 2026-05-27 | E8: 1410 | F8: 6 | G8: Payout complete | I8: =IF(H8<>"",E8-H8,"")
A9: 8 | B9: Fanatics Collect | C9: 2007 SP Authentic Kevin Durant ROOKIE AUTO /399 #152 PSA 8 NM-MT | D9: 2026-04-22 | E9: 1323.52 | F9: 6 | G9: Payout complete | I9: =IF(H9<>"",E9-H9,"")
A10: 9 | B10: Fanatics Collect | C10: 1987 Fleer Basketball Michael Jordan #59 PSA 8 NM-MT | D10: 2026-05-27 | E10: 1128 | F10: 6 | G10: Payout complete | I10: =IF(H10<>"",E10-H10,"")
A11: 10 | B11: Fanatics Collect | C11: 1997 Fleer Soaring Stars High Flying Michael Jordan #9 PSA 9 MINT | D11: 2026-06-11 | E11: 1034 | F11: 6 | G11: Payout complete | I11: =IF(H11<>"",E11-H11,"")
A12: 11 | B12: Fanatics Collect | C12: 2018 Panini Prizm World Cup Red Mosaic Kylian Mbappe ROOKIE #80 BGS 9.5 GEM MINT | D12: 2026-06-23 | E12: 1005.8 | F12: 6 | G12: Payout complete | I12: =IF(H12<>"",E12-H12,"")
A13: 12 | B13: Fanatics Collect | C13: 1988 Fleer Basketball Michael Jordan ALL-STAR #120 BGS 9 MINT | D13: 2026-06-21 | E13: 916.5 | F13: 6 | G13: Payout complete | I13: =IF(H13<>"",E13-H13,"")
... A28: 27 | B28: Fanatics Collect | C28: 2013 Fleer Retro '95 Metal Universe Precious Metal Gems Blue LeBron James /50 #247 BGS 8.5 | D28: 2026-06-14 | E28: 0 | F28: 0 | G28: Waiting for buyer's payment | I28: =IF(H28<>"",E28-H28,"")
D29: TOTALS | E29: =SUM(E2:E28) | H29: =SUM(H2:H28) | I29: =SUM(I2:I28)

Sheet Whatnot Matched
A1: # | B1: Platform | C1: Card | D1: Date | E1: Proceeds | F1: eBay Match | G1: eBay Cost | H1: Score | I1: CORRECTED COST | J1: Final Cost | K1: P&L | L1: Return
A2: 1 | B2: Whatnot | C2: 2024 Topps Heritage Chrome Hot Box Refractor Ronald Acuna Jr. ERROR #321 CGC AUTH | D2: 2026-04-12 | E2: 12.75 | F2: STEPHEN CURRY 2009-10 TOPPS ROOKIE CARD #321 NM-MT PSA 8 WARRIORS RC | G2: 2400 | H2: 12 | J2: =IF(I2<>"",I2,G2) | K2: =E2-J2 | L2: =IF(J2>0,K2/J2,"")
A3: 2 | B3: Whatnot | C3: 2023 Panini Court Kings Water Color Sapphire Anthony Edwards JERSEY # 5/25 #6 PSA 9 MINT | D3: 2026-03-22 | E3: 66.65 | F3: 2023 Select #16 Shai Gilgeous-Alexander Color Wheel Auto PSA MINT 9/GEM MINT 10 | G3: 2000 | H3: 17 | J3: =IF(I3<>"",I3,G3) | K3: =E3-J3 | L3: =IF(J3>0,K3/J3,"")
A4: 3 | B4: Whatnot | C4: 2025 Topps Season Tip-Off Green Josh Hart /99 #16 CGC AUTH | D4: 2026-03-22 | E4: 2.25 | F4: 2025-26 Topps Finest Stephen Curry #163 Uncommon Red Geometric Warriors /5 | G4: 1930 | H4: 17 | J4: =IF(I4<>"",I4,G4) | K4: =E4-J4 | L4: =IF(J4>0,K4/J4,"")
A5: 4 | B5: Whatnot | C5: 2024 Hoops Premium Green Scope Nikola Jokic /25 #12 CGC AUTH | D5: 2026-04-26 | E5: 16.95 | F5: 2024-25 Panini Noir Ja Morant Spotlight Signatures GOLD INK AUTO 12/99 Match 1/1 | G5: 1862 | H5: 15 | J5: =IF(I5<>"",I5,G5) | K5: =E5-J5 | L5: =IF(J5>0,K5/J5,"")
A6: 5 | B6: Whatnot | C6: 2025 Topps Chrome Refractor Victor Wembanyama #221 CGC AUTH | D6: 2026-05-03 | E6: 14.85 | F6: 2025-26 Topps Chrome - Victor Wembanyama #221 Orange Pulsar Refractor /25 | G6: 1450 | H6: 28 | J6: =IF(I6<>"",I6,G6) | K6: =E6-J6 | L6: =IF(J6>0,K6/J6,"")
A7: 6 | B7: Whatnot | C7: 2025 Topps Chrome Xfractor Victor Wembanyama #221 CGC AUTH | D7: 2026-05-03 | E7: 32.7 | F7: 2025-26 Topps Chrome - Victor Wembanyama #221 Orange Pulsar Refractor /25 | G7: 1450 | H7: 26 | J7: =IF(I7<>"",I7,G7) | K7: =E7-J7 | L7: =IF(J7>0,K7/J7,"")
A8: 7 | B8: Whatnot | C8: 2023 Bowman University Now Caitlin Clark ROOKIE #49 PSA 10 GEM MINT | D8: 2026-05-03 | E8: 31.65 | F8: JULIO RODRIGUEZ 2019 BOWMAN CHROME 1ST REFRACTOR AUTO /499 PSA 10 Q5878 | G8: 1448 | H8: 15 | J8: =IF(I8<>"",I8,G8) | K8: =E8-J8 | L8: =IF(J8>0,K8/J8,"")
A9: 8 | B9: Whatnot | C9: 2024 Topps Chrome Red Geometric Refractor Dwyane Wade 5/5 #13 CGC AUTH | D9: 2026-03-22 | E9: 18 | F9: KEVIN DURANT PSA 9 2007-08 TOPPS CHROME #131 ROOKIE REFRACTOR RC 0641/1499 | G9: 1275 | H9: 19 | J9: =IF(I9<>"",I9,G9) | K9: =E9-J9 | L9: =IF(J9>0,K9/J9,"")
A10: 9 | B10: Whatnot | C10: 2021 Panini Flawless Draft Gem Luka Doncic AUTO /25 #DGS-LDD | D10: 2026-02-21 | E10: 1155 | F10: 2021-22 Panini Flawless Luka Doncic #DGS-LDD Draft Gem Signatures Auto /25 | G10: 2411 | H10: 30 | J10: =IF(I10<>"",I10,G10) | K10: =E10-J10 | L10: =IF(J10>0,K10/J10,"")
A11: 10 | B11: Whatnot | C11: 2025 Topps Chrome Cooper Flagg ROOKIE #251 CGC AUTH | D11: 2026-03-22 | E11: 15.9 | F11: 2025-26 Topps Chrome - Cooper Flagg #251 Green Basketball Refractor /99 (RC) | G11: 1150 | H11: 26 | J11: =IF(I11<>"",I11,G11) | K11: =E11-J11 | L11: =IF(J11>0,K11/J11,"")
A12: 11 | B12: Whatnot | C12: 2019 Panini Flawless Collegiate Star Swatch Gold Donovan Mitchell PATCH AUTO /10 #17 CGC AUTH | D12: 2026-05-03 | E12: 163.625 | F12: 2017-18 Panini Flawless Giannis Antetokounmpo Momentous Auto Gold /10 | G12: 1125 | H12: 19 | J12: =IF(I12<>"",I12,G12) | K12: =E12-J12 | L12: =IF(J12>0,K12/J12,"")
A13: 12 | B13: Whatnot | C13: 2024 Panini Prizm Black Prizmatrix Gold Shimmer Luka Doncic AUTO 1/10 #PS-LUK | D13: 2026-02-21 | E13: 1980 | F13: 1/10 ≈1/1 ! 2024-25 Panini Prizm Black Luka Doncic Gold Shimmer Prizmatrix Auto | G13: 2817 | H13: 29 | J13: =IF(I13<>"",I13,G13) | K13: =E13-J13 | L13: =IF(J13>0,K13/J13,"")
... A140: 139 | B140: Whatnot | C140: 2020 National Treasures Colossal White Box Tyrese Maxey ROOKIE PATCH AUTO 1/1 #CM-TMX | D140: 2026-02-21 | E140: 990 | F140: Tyrese Maxey 2020-21 Panini Prizm Penmanship #RP-TMX PSA 10 MINT Rookie Auto RC | G140: 340 | H140: 14 | J140: =IF(I140<>"",I140,G140) | K140: =E140-J140 | L140: =IF(J140>0,K140/J140,"")
D142: TOTALS: | E142: =SUM(E2:E140) | J142: =SUM(J2:J140) | K142: =SUM(K2:K140) | L142: =IF(J142>0,K142/J142,"")

Sheet Whatnot Unmatched
A1: # | B1: Platform | C1: Card | D1: Date | E1: Proceeds | F1: Best Guess | G1: Guess Cost | H1: YOUR COST | I1: P&L | J1: Return
A2: 1 | B2: Whatnot | C2: 2022 National Treasures Treasured Moments '25 Black Box Stephen Curry AUTO 1/1 #TM-SCY | D2: 2026-02-21 | E2: 2860 | G2: 0 | I2: =IF(H2<>"",E2-H2,"") | J2: =IF(H2<>"",I2/H2,"")
A3: 2 | B3: Whatnot | C3: 2020 National Treasures Horizontal '25 Black Box Tyrese Maxey ROOKIE PATCH AUTO 1/1 #114 | D3: 2026-02-21 | E3: 1155 | G3: 0 | I3: =IF(H3<>"",E3-H3,"") | J3: =IF(H3<>"",I3/H3,"")
A4: 3 | B4: Whatnot | C4: 2024 Bowman Chrome Draft Black Refractor Sam Antonacci PROSPECT AUTO 1/10 #CPA-SA CGC AUTH | D4: 2026-03-22 | E4: 877 | G4: 0 | I4: =IF(H4<>"",E4-H4,"") | J4: =IF(H4<>"",I4/H4,"")
A5: 4 | B5: Whatnot | C5: 2024 Panini Flawless Mastercraft Jayson Tatum PATCH /5 #MC-JYT CGC AUTH | D5: 2026-03-29 | E5: 822 | G5: 0 | I5: =IF(H5<>"",E5-H5,"") | J5: =IF(H5<>"",I5/H5,"")
A6: 5 | B6: Whatnot | C6: 2024 Topps Transcendent Collection Showcase Blue Paul Skenes ROOKIE AUTO /10 #RSA-PS | D6: 2026-02-21 | E6: 770 | G6: 0 | I6: =IF(H6<>"",E6-H6,"") | J6: =IF(H6<>"",I6/H6,"")
A7: 6 | B7: Whatnot | C7: 2022 National Treasures Clutch Factor '25 Black Box Paolo Banchero ROOKIE PATCH AUTO 1/1 | D7: 2026-02-21 | E7: 605 | G7: 0 | I7: =IF(H7<>"",E7-H7,"") | J7: =IF(H7<>"",I7/H7,"")
A8: 7 | B8: Whatnot | C8: 2023 Topps Dynasty Silver Vladimir Guerrero Jr. PATCH AUTO /5 #DAPB-VGJ1 | D8: 2026-02-21 | E8: 506 | G8: 0 | I8: =IF(H8<>"",E8-H8,"") | J8: =IF(H8<>"",I8/H8,"")
A9: 8 | B9: Whatnot | C9: 2024 Bowman University Best Greatness Awaits Gold Geometric Kon Knueppel RC AUTO /50 CGC AUTH | D9: 2026-03-01 | E9: 349 | G9: 0 | I9: =IF(H9<>"",E9-H9,"") | J9: =IF(H9<>"",I9/H9,"")
A10: 9 | B10: Whatnot | C10: 2025 Bowman Chrome Yellow Refractor Charlie Condon PROSPECT AUTO /75 #CPA-CC CGC AUTH | D10: 2026-04-12 | E10: 349 | G10: 0 | I10: =IF(H10<>"",E10-H10,"") | J10: =IF(H10<>"",I10/H10,"")
A11: 10 | B11: Whatnot | C11: 2021 Select Black Snakeskin Pulsar Bones Hyland ROOKIE PATCH AUTO 1/1 #RJ-BHY CGC AUTH | D11: 2026-02-21 | E11: 338 | G11: 0 | I11: =IF(H11<>"",E11-H11,"") | J11: =IF(H11<>"",I11/H11,"")
A12: 11 | B12: Whatnot | C12: 2021 Immaculate Collection Massive Memorabilia Cade Cunningham ROOKIE PATCH 25/25 CGC AUTH | D12: 2026-02-21 | E12: 305 | G12: 0 | I12: =IF(H12<>"",E12-H12,"") | J12: =IF(H12<>"",I12/H12,"")
A13: 12 | B13: Whatnot | C13: 2022 Panini One And One Purple Paolo Banchero ROOKIE PATCH AUTO 35/35 #RJA-PB5 | D13: 2026-02-21 | E13: 286 | G13: 0 | I13: =IF(H13<>"",E13-H13,"") | J13: =IF(H13<>"",I13/H13,"")
... A94: 93 | B94: Whatnot | C94: 2025 Topps Chrome Inspirational Raywave Refractor Victor Wembanyama #IP-6 CGC AUTH | D94: 2026-05-03 | E94: 2.25 | G94: 0 | I94: =IF(H94<>"",E94-H94,"") | J94: =IF(H94<>"",I94/H94,"")
D96: TOTALS: | E96: =SUM(E2:E94) | H96: =SUM(H2:H94) | I96: =SUM(I2:I94)

Sheet SUMMARY
A1: CROSS-PLATFORM TAX P&L SUMMARY
A3: Platform | B3: Proceeds | C3: Cost Basis | D3: P&L | E3: Return
A4: Goldin (matched) | B4: ='Goldin Matched'!E265 | C4: ='Goldin Matched'!J265 | D4: ='Goldin Matched'!K265 | E4: =IF(C4>0,D4/C4,"")
A5: Goldin (unmatched) | B5: ='Goldin Unmatched'!E85 | C5: ='Goldin Unmatched'!G85 | D5: ='Goldin Unmatched'!H85 | E5: =IF(C5>0,D5/C5,"")
A6: Fanatics Collect (matched) | B6: ='FC Matched'!E63 | C6: ='FC Matched'!K63 | D6: ='FC Matched'!L63 | E6: =IF(C6>0,D6/C6,"")
A7: Fanatics Collect (unmatched) | B7: ='FC Unmatched'!E29 | C7: ='FC Unmatched'!H29 | D7: ='FC Unmatched'!I29 | E7: =IF(C7>0,D7/C7,"")
A8: Whatnot/Fanatics (matched) | B8: ='Whatnot Matched'!E142 | C8: ='Whatnot Matched'!J142 | D8: ='Whatnot Matched'!K142 | E8: =IF(C8>0,D8/C8,"")
A9: Whatnot/Fanatics (unmatched) | B9: ='Whatnot Unmatched'!E96 | C9: ='Whatnot Unmatched'!H96 | D9: ='Whatnot Unmatched'!I96 | E9: =IF(C9>0,D9/C9,"")
A11: TOTAL (ALL PLATFORMS) | B11: =SUM(B4:B9) | C11: =SUM(C4:C9) | D11: =SUM(D4:D9) | E11: =IF(C11>0,D11/C11,"")
A13: eBay Total Purchases (cost basis pool) | B13: 2375205
A14: Cost basis in unsold inventory | B14: =B13-C11
A16: NOTES:
A17: Yellow columns = enter your actual eBay cost to correct bad auto-matches
A18: Fanatics Collect = PSA Vault / fanaticscollect.com Buy Now sales (6-12% seller fee)
A19: Whatnot/Fanatics = live auction sales (Whatnot platform, now owned by Fanatics)
A20: Goldin = auction consignment (seller gets hammer x 1.15)
A21: IMPORTANT: Many auto-matched eBay costs are WRONG. Verify before filing taxes.
A22: 4 Fanatics Collect sales still awaiting buyer payment (show $0 net)
