Workbook

Sheet Matched - Verify
A1: # | B1: Goldin Card | C1: Auction | D1: Goldin Final (w/BP) | E1: Seller Proceeds | F1: Matched eBay Purchase | G1: eBay Cost | H1: Score | I1: CORRECTED COST | J1: Final Cost | K1: P&L | L1: Return
A2: 1 | B2: 1986-87 Fleer #7 Charles Barkley Signed Rookie Card - PSA Authentic, PSA/DNA Authentic | C2: 2026 Weekly Auction Apr 21 - Apr 30 | D2: 388 | E2: 365.74 | F2: 1986-87 Fleer - Michael Jordan 🐐 #57 (RC) PSA 8 !!! ROOKIE - GORGEOUS !!! | G2: 8500 | H2: 21 | J2: =IF(I2<>"",I2,G2) | K2: =E2-J2 | L2: =IF(J2>0,K2/J2,"")
A3: 2 | B3: 2024 Panini NSCC VIP Gold Purple Sparkle #1 Caitlin Clark Rookie Card (#32/49) - PSA NM-MT 8 | C3: 2026 Weekly Auction Mar 24 - Apr 2 | D3: 155 | E3: 146.11 | F3: 2024 Select WNBA #38 Caitlin Clark Rookie Purple Memorabilia /49 PSA GEM 10 AUTO | G3: 7000 | H3: 25 | J3: =IF(I3<>"",I3,G3) | K3: =E3-J3 | L3: =IF(J3>0,K3/J3,"")
A4: 3 | B4: 2024 Panini Select Sparks Memorabilia Purple Prizm #38 Caitlin Clark Signed Relic Rookie Card (#26/49) - PSA Authentic, PSA/DNA GEM MT 10 | C4: 2026 Weekly Auction May 12 - May 21 | D4: 436 | E4: 410.98 | F4: 2024 Select WNBA #38 Caitlin Clark Rookie Purple Memorabilia /49 PSA GEM 10 AUTO | G4: 7000 | H4: 30 | J4: =IF(I4<>"",I4,G4) | K4: =E4-J4 | L4: =IF(J4>0,K4/J4,"")
A5: 4 | B5: 2024 Panini Prizm #22 Caitlin Clark Rookie Card - PSA GEM MT 10 | C5: 2026 Weekly Auction May 5 - May 14 | D5: 175 | E5: 164.96 | F5: 2024 Panini Prizm WNBA #22 Caitlin Clark Orange Ice Rookie PSA GEM MINT 10 AUTO | G5: 5000 | H5: 23 | J5: =IF(I5<>"",I5,G5) | K5: =E5-J5 | L5: =IF(J5>0,K5/J5,"")
A6: 5 | B6: 1997-98 Topps Stadium Club Triumvirate Luminous #T9B Michael Jordan - PSA NM-MT 8 | C6: 2026 April Elite Auction | D6: 1255 | E6: 1182.99 | F6: 1997-98 Stadium Club Triumvirate - Michael Jordan #T9B BGS 9.5 | G6: 6000 | H6: 28 | J6: =IF(I6<>"",I6,G6) | K6: =E6-J6 | L6: =IF(J6>0,K6/J6,"")
A7: 6 | B7: 2024 Panini Prizm WNBA Blue Velocity Prizm #22 Caitlin Clark Rookie Card - PSA GEM MT 10 | C7: 2026 Weekly Auction May 5 - May 14 | D7: 350 | E7: 329.92 | F7: 2024 Panini Prizm WNBA #22 Caitlin Clark Orange Ice Rookie PSA GEM MINT 10 AUTO | G7: 5000 | H7: 23 | J7: =IF(I7<>"",I7,G7) | K7: =E7-J7 | L7: =IF(J7>0,K7/J7,"")
A8: 7 | B8: 2014-15 Upper Deck SP Authentic Immortal Ink #II-JO Michael Jordan Signed Card (#2/3) - BGS GEM MINT 9.5 - Pop 2 | C8: 2026 April Elite Auction | D8: 8388 | E8: 7906.72 | F8: MICHAEL JORDAN BGS 9.5 2014-15 SP AUTHENTIC #II-JO IMMORTAL INK ON CARD AUTO 2/3 | G8: 11700 | H8: 29 | J8: =IF(I8<>"",I8,G8) | K8: =E8-J8 | L8: =IF(J8>0,K8/J8,"")
A9: 8 | B9: 2022-23 Panini Flawless Autographs Emerald '25 Black Box #FA-SGA Shai Gilgeous-Alexander Signed Card (#1/1) - Panini Encased | C9: 2026 April Elite Auction | D9: 1700 | E9: 1602.46 | F9: SHAI GILGEOUS-ALEXANDER 2018-19 PANINI FLAWLESS #RA-SGA ROOKIE AUTO RUBY RC 9/15 | G9: 5100 | H9: 18 | J9: =IF(I9<>"",I9,G9) | K9: =E9-J9 | L9: =IF(J9>0,K9/J9,"")
A10: 9 | B10: 2001-02 Topps Pristine Refractor #6 Michael Jordan (#21/50) - PSA GEM MT 10 | C10: 2026 Weekly Auction Mar 31 - Apr 9 | D10: 6001 | E10: 5656.68 | F10: 1996-97 Finest Michael Jordan W/Coating Gold Refractor #291 Bulls PSA 9 | G10: 9005 | H10: 15 | J10: =IF(I10<>"",I10,G10) | K10: =E10-J10 | L10: =IF(J10>0,K10/J10,"")
A11: 10 | B11: 2021-22 Panini National Treasures Clutch Factor Signatures #CF-SCU Stephen Curry Signed Relic Card (#09/25) - Panini Encased | C11: 2026 March Elite Auction | D11: 1500 | E11: 1413.93 | F11: 2023 Panini Flawless Stephen Curry Scoring Title Auto #FST-SCU /25 PSA 9/10 | G11: 4350 | H11: 12 | J11: =IF(I11<>"",I11,G11) | K11: =E11-J11 | L11: =IF(J11>0,K11/J11,"")
A12: 11 | B12: 2022-23 Panini National Treasures Rookie Patch Autographs Ruby '25 Black Box #110 Paolo Banchero Signed Patch Rookie Card (#1/1) - Panini Encased | C12: 2026 April Elite Auction | D12: 1650 | E12: 1555.33 | F12: PAOLO BANCHERO 2022-23 NATIONAL TREASURES #110 ROOKIE PATCH AUTO RPA B/BX 1/1 | G12: 4029 | H12: 28 | J12: =IF(I12<>"",I12,G12) | K12: =E12-J12 | L12: =IF(J12>0,K12/J12,"")
A13: 12 | B13: 1996-97 Topps NBA Stars Finest #124 Michael Jordan - PSA GEM MT 10 | C13: 2026 April Elite Auction | D13: 700 | E13: 659.84 | F13: 1996 Topps Stars Michael Jordan Finest Refractor #124 PSA 10 | G13: 3050 | H13: 21 | J13: =IF(I13<>"",I13,G13) | K13: =E13-J13 | L13: =IF(J13>0,K13/J13,"")
... A145: 144 | B145: 2019 Panini Industry Summit 2015-16 National Treasures Rookie Autograph #152 Nikola Jokic Signed Rookie Card (#1/1) - PSA MINT 9, PSA/DNA GEM MT 10 | C145: 2026 March Elite Auction | D145: 9000 | E145: 8483.61 | F145: JARED MCCAIN 2024-25 OBSIDIAN ROOKIE GOLD FLOOD ETCH #152 RC /10 PSA 9 Q4945 | G145: 114.05 | H145: 14 | J145: =IF(I145<>"",I145,G145) | K145: =E145-J145 | L145: =IF(J145>0,K145/J145,"")
D147: TOTALS: | E147: =SUM(E2:E145) | J147: =SUM(J2:J145) | K147: =SUM(K2:K145) | L147: =IF(J147>0,K147/J147,"")

Sheet Unmatched - Enter Cost
A1: # | B1: Goldin Card | C1: Auction | D1: Goldin Final (w/BP) | E1: Seller Proceeds | F1: Best Guess Match | G1: Guess Cost | H1: YOUR COST ← ENTER | I1: P&L | J1: Return
A2: 1 | B2: 2019 Panini Flawless Triple Legends Sapphire #TL-MRG Mickey Mantle/Babe Ruth/Lou Gehrig Relic Card (#05/15) - PSA GEM MT 10 - Pop 2 | C2: 2026 Weekly Auction Mar 24 - Apr 2 | D2: 7001 | E2: 6599.3 | G2: 0 | I2: =IF(H2<>"",E2-H2,"") | J2: =IF(H2<>"",I2/H2,"")
A3: 2 | B3: 2023-24 Topps Chrome 1972 Topps Autographs Gold Refractor #TA-VW Victor Wembanyama Signed Rookie Card (#04/50) - PSA MINT 9 | C3: 2026 Weekly Auction May 19 - May 28 | D3: 6194 | E3: 5838.61 | G3: 0 | I3: =IF(H3<>"",E3-H3,"") | J3: =IF(H3<>"",I3/H3,"")
A4: 3 | B4: 2018-19 Panini National Treasures Peerless Signatures #PS-KBR Kobe Bryant Signed Card (#03/25) - BGS MINT 9, Beckett 10 | C4: 2026 April Elite Auction | D4: 3500 | E4: 3299.18 | G4: 0 | I4: =IF(H4<>"",E4-H4,"") | J4: =IF(H4<>"",I4/H4,"")
A5: 4 | B5: 2015-16 Panini Noir Autographs Color Gold #NC-KBR Kobe Bryant Signed Card (#4/5) - PSA EX-MT 6 - Pop 1 | C5: 2026 March Elite Auction | D5: 3300 | E5: 3110.66 | G5: 0 | I5: =IF(H5<>"",E5-H5,"") | J5: =IF(H5<>"",I5/H5,"")
A6: 5 | B6: 2013 Upper Deck All-Time Greats Signatures Silver #ATG-LJ3 LeBron James Signed Card (#3/5) - BGS MINT 9, Beckett 10 | C6: 2026 April Elite Auction | D6: 3256 | E6: 3069.18 | G6: 0 | I6: =IF(H6<>"",E6-H6,"") | J6: =IF(H6<>"",I6/H6,"")
A7: 6 | B7: 2003-04 Upper Deck Top Prospects Signs of Success #SS-LJ LeBron James Signed Rookie Card - BGS MINT 9, Beckett 10 | C7: 2026 April Elite Auction | D7: 2650 | E7: 2497.95 | G7: 0 | I7: =IF(H7<>"",E7-H7,"") | J7: =IF(H7<>"",I7/H7,"")
A8: 7 | B8: 2025 Panini Impeccable WNBA Basketball Factory-Sealed Hobby Case (3 Boxes) - Possible Paige Bueckers, Hailey Van Lith, Kiki Iriafen Rookie Cards | C8: 2026 Weekly Auction Mar 3 - Mar 12 | D8: 2501 | E8: 2357.5 | G8: 0 | I8: =IF(H8<>"",E8-H8,"") | J8: =IF(H8<>"",I8/H8,"")
A9: 8 | B9: 2023-24 Bowman U Best of 2023 Autograph Geometric Red Refractor #B23-CC Caitlin Clark Signed Rookie Card (#01/10) - PSA MINT 9, PSA/DNA GEM MT 10 | C9: 2026 Weekly Auction Mar 24 - Apr 2 | D9: 2300 | E9: 2168.03 | G9: 0 | I9: =IF(H9<>"",E9-H9,"") | J9: =IF(H9<>"",I9/H9,"")
A10: 9 | B10: 2020-21 Panini Flawless Draft Gem Signatures Ruby #DG-AEW Anthony Edwards Signed Rookie Card (#15/15) - Panini Encased | C10: 2026 Weekly Auction Mar 24 - Apr 2 | D10: 2262 | E10: 2132.21 | G10: 0 | I10: =IF(H10<>"",E10-H10,"") | J10: =IF(H10<>"",I10/H10,"")
A11: 10 | B11: 2022-23 Bowman U Best of '22 Autographs #BOA-VW Victor Wembanyama Signed Rookie Card - PSA GEM MT 10 | C11: 2026 Weekly Auction Mar 24 - Apr 2 | D11: 2150 | E11: 2026.64 | G11: 0 | I11: =IF(H11<>"",E11-H11,"") | J11: =IF(H11<>"",I11/H11,"")
A12: 11 | B12: 2025-26 Topps Chrome Next Stop Signatures Purple Geometric Refractor #NS-CF Cooper Flagg Signed Rookie Card (#68/75) - PSA MINT 9 | C12: 2026 April Elite Auction | D12: 2066 | E12: 1947.46 | G12: 0 | I12: =IF(H12<>"",E12-H12,"") | J12: =IF(H12<>"",I12/H12,"")
A13: 12 | B13: 2023 Bowman Draft Picks & Prospects Autographs Red #DPPA-PS Paul Skenes Signed Rookie Card (#2/5) - PSA MINT 9 | C13: 2026 April Elite Auction | D13: 2000 | E13: 1885.25 | G13: 0 | I13: =IF(H13<>"",E13-H13,"") | J13: =IF(H13<>"",I13/H13,"")
... A72: 71 | B72: 2022-23 Panini Immaculate Collection Patch Autographs Jersey Number #IPA-RGO Rudy Gobert Signed Relic Card (#06/27) - Panini Encased | C72: 2026 Weekly Auction Apr 21 - Apr 30 | D72: 24 | E72: 22.62 | G72: 0 | I72: =IF(H72<>"",E72-H72,"") | J72: =IF(H72<>"",I72/H72,"")
D74: TOTALS: | E74: =SUM(E2:E72) | H74: =SUM(H2:H72) | I74: =SUM(I2:I72)

Sheet Summary
A1: GOLDIN TAX P&L SUMMARY
A3: Total cards sold | B3: 215
A4: Cards with eBay cost match | B4: 144
A5: Cards needing manual cost | B5: 71
A7: MATCHED CARDS
A8: Total Goldin proceeds | B8: ='Matched - Verify'!E147
A9: Total eBay cost basis | B9: ='Matched - Verify'!J147
A10: Net P&L (matched) | B10: ='Matched - Verify'!K147
A12: UNMATCHED CARDS
A13: Total Goldin proceeds | B13: ='Unmatched - Enter Cost'!E74
A14: Total eBay cost basis (entered) | B14: ='Unmatched - Enter Cost'!H74
A15: Net P&L (unmatched) | B15: ='Unmatched - Enter Cost'!I74
A17: COMBINED TOTAL P&L | B17: =B10+B15
A19: INSTRUCTIONS
A20: 1. 'Matched' tab: verify auto-matches, correct Column I if wrong
A21: 2. 'Unmatched' tab: enter your eBay cost in Column H
A22: 3. Summary tab auto-calculates combined P&L
A23: 4. Upload corrected file back for final report
A25: Seller proceeds = (Goldin Final ÷ 1.22) × 1.15
A26: P&L = Seller Proceeds - Cost Basis
